postgresql_mcp_server/__init__.py
postgresql_mcp_server/__main__.py
postgresql_mcp_server/cli.py
postgresql_mcp_server/server.py
postgresql_mcp_server/tools/__init__.py
postgresql_mcp_server/tools/registry.py
postgresql_mcp_server/utils/__init__.py
postgresql_mcp_server/utils/client.py
postgresql_mcp_server/utils/helpers.py
msrashed_postgresql_mcp_server-0.1.0.dist-info/METADATA
msrashed_postgresql_mcp_server-0.1.0.dist-info/WHEEL
msrashed_postgresql_mcp_server-0.1.0.dist-info/entry_points.txt
msrashed_postgresql_mcp_server-0.1.0.dist-info/licenses/LICENSE
msrashed_postgresql_mcp_server-0.1.0.dist-info/RECORD
