Metadata-Version: 2.4
Name: msrashed-postgresql-mcp-server
Version: 0.1.0
Summary: Read-only PostgreSQL MCP server for database inspection, querying, and performance analysis
Project-URL: Homepage, https://github.com/msalah-eg/postgresql-mcp-server
Project-URL: Repository, https://github.com/msalah-eg/postgresql-mcp-server
Project-URL: Issues, https://github.com/msalah-eg/postgresql-mcp-server/issues
Author-email: Mohamed Salah <mohamed@buyinggroup.com>
License: MIT
License-File: LICENSE
Keywords: ai,database,llm,mcp,model-context-protocol,postgres,postgresql,sql
Classifier: Development Status :: 4 - Beta
Classifier: Intended Audience :: Developers
Classifier: License :: OSI Approved :: MIT License
Classifier: Programming Language :: Python :: 3.12
Classifier: Programming Language :: Python :: 3.13
Classifier: Topic :: Database
Classifier: Topic :: Software Development :: Libraries :: Python Modules
Requires-Python: >=3.12
Requires-Dist: click>=8.1.0
Requires-Dist: fastmcp>=2.0.0
Requires-Dist: mcp>=1.24.0
Requires-Dist: psycopg[binary]>=3.1.0
Requires-Dist: pydantic>=2.0.0
Provides-Extra: dev
Requires-Dist: pytest-asyncio>=0.24.0; extra == 'dev'
Requires-Dist: pytest>=8.0.0; extra == 'dev'
Requires-Dist: ruff>=0.8.0; extra == 'dev'
